{
	"Theme": { "pl": "Motyw", "de": "Motiv" },
	"Button": { "pl": "Przycisk", "de": "Knopf" },
	"Log in": { "pl": "Zaloguj się", "de": "Anmelden" },
	"Login": { "pl": "Login", "de": "Login" },
	"Register": { "pl": "Zarejestruj się", "de": "Registrieren" },
	"Dashboard": { "pl": "Panel", "de": "Bedienpult" },
	"Home": { "pl": "Strona Główna", "de": "Startseite" },
	"Settings": { "pl": "Ustawienia", "de": "Einstellungen" },
	"Account": { "pl": "Konto", "de": "Konto" },
	"Logout": { "pl": "Wyloguj się", "de": "Ausloggen" },
	"Overview": { "pl": "Przegląd", "de": "Überblick" },
	"Password": { "pl": "Hasło", "de": "Passwort" },
	"Confirm Password": { "pl": "Potwierdź Hasło", "de": "Bestätige das Passwort" },
	"Send": { "pl": "Wyślij", "de": "Send" },
	"Remove": { "pl": "Usuń", "de": "Entfernen" },
	"Yes": { "pl": "Tak", "de": "Ja" },
	"No": { "pl": "Nie", "de": "Nein" },
	"Pages": { "pl": "Strony", "de": "Seiten" },
	"Contact": { "pl": "Kontakt", "de": "Kontakt" },
	"Light": { "pl": "Jasny", "de": "Hell" },
	"Dark": { "pl": "Ciemny", "de": "Dunkel" },
	"Name": { "pl": "Nazwa", "de": "Name" },
	"Refuel": { "pl": "Tankowanie", "de": "Tanken" },
	"About": { "pl": "O aplikacji", "de": "Über App" },
	"Cost": { "pl": "Koszt", "de": "Kosten" },
	"Fuel": { "pl": "Paliwo", "de": "Kraftstoff" },
	"Distance": { "pl": "Dystans", "de": "Distanz" },
	"Fuel/Cost": { "pl": "Paliwo/Koszt", "de": "Treibstoff/Kosten" },
	"Cost/Fuel": { "pl": "Koszt/Paliwo", "de": "Kosten/Treibstoff" },
	"Fuel/Distance": { "pl": "Paliwo/Dystans", "de": "Treibstoff/Distanz" },
	"Distance/Fuel": { "pl": "Dystans/Paliwo", "de": "Distanz/Treibstoff" },
	"Cost/Distance": { "pl": "Koszt/Dystans", "de": "Kosten/Distanz" },
	"Distance/Cost": { "pl": "Dystans/Koszt", "de": "Distanz/Kosten" },
	"Event": { "pl": "Wydarzenie", "de": "Fall" },
	"Last refuel": { "pl": "Ostatnie tankowanie", "de": "Letztes Auftanken" },
	"Preferences": { "pl": "Preferencje", "de": "" }
}
